updns/__init__.py
updns/updns.py
updns-2.0.dist-info/METADATA
updns-2.0.dist-info/WHEEL
updns-2.0.dist-info/entry_points.txt
updns-2.0.dist-info/top_level.txt
updns-2.0.dist-info/zip-safe
updns-2.0.dist-info/RECORD
