Metadata-Version: 2.1
Name: updns
Version: 2.0
Summary: 用于更新本地自定义域名的DNS解析记录，以确保正常访问服务。
Author: sanfeng
License: MIT
Keywords: python、PyPi source、terminal
Requires-Dist: rich
